LICENSE
MANIFEST.in
README.md
setup.py
imagemp/__init__.py
imagemp.egg-info/PKG-INFO
imagemp.egg-info/SOURCES.txt
imagemp.egg-info/dependency_links.txt
imagemp.egg-info/not-zip-safe
imagemp.egg-info/top_level.txt
imagemp/process_runners/__init__.py
imagemp/process_runners/abstract.py
imagemp/process_runners/consumer.py
imagemp/process_runners/frame_grabber.py
imagemp/process_runners/run_script1.py
imagemp/process_runners/shared_events.py
imagemp/process_runners/timers.py
imagemp/process_runners/examples/__init__.py
imagemp/process_runners/examples/recorder.py
imagemp/process_runners/examples/simple_display.py
imagemp/process_runners/examples/tracker_fish4.py
imagemp/scheduler/__init__.py
imagemp/scheduler/scheduler.py
imagemp/shared_frames/__init__.py
imagemp/shared_frames/abstract_struct.py
imagemp/shared_frames/list_frames.py
imagemp/shared_frames/misc.py
imagemp/shared_frames/shared_frame.py
imagemp/shared_frames/single_frame.py
imagemp/shared_frames/value_change_event.py
imagemp/shframe_grabbers/__init__.py
imagemp/shframe_grabbers/abstract.py
imagemp/shframe_grabbers/factory.py
imagemp/shframe_grabbers/file_grabber.py
imagemp/shframe_grabbers/opencv_grabber.py
imagemp/shframe_grabbers/skvideo_grabber.py