Metadata-Version: 1.0
Name: imagemp
Version: 0.1.2
Summary: Process image sequences in multiple processes with shared memory areas
Home-page: UNKNOWN
Author: Max Nikitchenko
Author-email: nikitchmtech@gmail.com
License: MIT
Platform: UNKNOWN
